usf_p1_chatbot_sdk/__init__.py
usf_p1_chatbot_sdk/base_client.py
usf_p1_chatbot_sdk/client.py
usf_p1_chatbot_sdk/exceptions.py
usf_p1_chatbot_sdk/endpoints/__init__.py
usf_p1_chatbot_sdk/endpoints/chat.py
usf_p1_chatbot_sdk/endpoints/collections.py
usf_p1_chatbot_sdk/endpoints/files.py
usf_p1_chatbot_sdk/endpoints/ingestion.py
usf_p1_chatbot_sdk/endpoints/logs.py
usf_p1_chatbot_sdk/endpoints/patients.py
usf_p1_chatbot_sdk-2.0.3.dist-info/licenses/LICENSE
usf_p1_chatbot_sdk-2.0.3.dist-info/METADATA
usf_p1_chatbot_sdk-2.0.3.dist-info/WHEEL
usf_p1_chatbot_sdk-2.0.3.dist-info/top_level.txt
usf_p1_chatbot_sdk-2.0.3.dist-info/RECORD
