Metadata-Version: 2.4
Name: usf-p1-chatbot-sdk
Version: 2.0.3
Summary: Python SDK for Civie Chatbot API v2.0.3 with comprehensive endpoint coverage
Home-page: https://github.com/ultrasafe/usf-p1-chatbot-sdk
Author: USF Team
Author-email: USF Team <support@ultrasafe.com>
License: MIT
Project-URL: Homepage, https://github.com/ultrasafe/usf-p1-chatbot-sdk
Project-URL: Documentation, https://github.com/ultrasafe/usf-p1-chatbot-sdk/blob/main/README.md
Project-URL: Repository, https://github.com/ultrasafe/usf-p1-chatbot-sdk
Project-URL: Bug Tracker, https://github.com/ultrasafe/usf-p1-chatbot-sdk/issues
Project-URL: API Documentation, https://api-civie.us.inc/docs
Keywords: civie,chatbot,api,sdk,healthcare,patient management,rag,llm,medical records,document ingestion
Classifier: Development Status :: 5 - Production/Stable
Classifier: Intended Audience :: Developers
Classifier: Intended Audience :: Healthcare Industry
Classifier: Topic :: Software Development :: Libraries :: Python Modules
Classifier: Topic :: Scientific/Engineering :: Artificial Intelligence
Classifier: License :: OSI Approved :: MIT License
Classifier: Programming Language :: Python :: 3
Classifier: Programming Language :: Python :: 3.8
Classifier: Programming Language :: Python :: 3.9
Classifier: Programming Language :: Python :: 3.10
Classifier: Programming Language :: Python :: 3.11
Classifier: Programming Language :: Python :: 3.12
Classifier: Operating System :: OS Independent
Requires-Python: >=3.8
License-File: LICENSE
Requires-Dist: requests>=2.31.0
Provides-Extra: dev
Requires-Dist: pytest>=7.0.0; extra == "dev"
Requires-Dist: pytest-cov>=4.0.0; extra == "dev"
Requires-Dist: black>=23.0.0; extra == "dev"
Requires-Dist: flake8>=6.0.0; extra == "dev"
Requires-Dist: mypy>=1.0.0; extra == "dev"
Requires-Dist: build>=0.10.0; extra == "dev"
Requires-Dist: twine>=4.0.0; extra == "dev"
Dynamic: author
Dynamic: home-page
Dynamic: license-file
Dynamic: requires-python
